versioninfo_helper/__init__.py
versioninfo_helper/py.typed
versioninfo_helper-1.0.0.3.dist-info/licenses/LICENSE.txt
versioninfo_helper-1.0.0.3.dist-info/METADATA
versioninfo_helper-1.0.0.3.dist-info/WHEEL
versioninfo_helper-1.0.0.3.dist-info/top_level.txt
versioninfo_helper-1.0.0.3.dist-info/RECORD
