Metadata-Version: 2.4
Name: versioninfo_helper
Version: 1.0.0.3
Summary: VersionInfo helper script for PyInstaller
Author-email: ReggX <dev@reggx.eu>
License-Expression: MIT
Project-URL: Homepage, https://github.com/ReggX/versioninfo_helper
Project-URL: Documentation, https://reggx.github.io/versioninfo_helper/
Project-URL: PyPI, https://pypi.org/project/versioninfo-helper/
Project-URL: Bug Reports, https://github.com/ReggX/versioninfo_helper/issues
Project-URL: Source, https://github.com/ReggX/versioninfo_helper
Keywords: PyInstaller,VersionInfo,development
Classifier: Development Status :: 5 - Production/Stable
Classifier: Intended Audience :: Developers
Classifier: Programming Language :: Python :: 3
Classifier: Programming Language :: Python :: 3.9
Classifier: Programming Language :: Python :: 3.10
Classifier: Programming Language :: Python :: 3.11
Classifier: Programming Language :: Python :: 3.12
Classifier: Programming Language :: Python :: 3.13
Classifier: Programming Language :: Python :: 3.14
Classifier: Programming Language :: Python :: 3 :: Only
Classifier: Operating System :: Microsoft :: Windows
Classifier: Environment :: Win32 (MS Windows)
Classifier: Topic :: Software Development :: Libraries
Classifier: Typing :: Typed
Requires-Python: >=3.9
License-File: LICENSE.txt
Requires-Dist: pyinstaller>=5; python_version < "3.12"
Requires-Dist: pyinstaller>=5.5; python_version >= "3.11"
Requires-Dist: pyinstaller>=5.13; python_version >= "3.12"
Requires-Dist: typing-extensions>=4.13.2; python_version < "3.15"
Dynamic: license-file
